llm_functions/__init__.py
llm_functions/llm_function.py
llm_functions-0.1.21.dist-info/LICENSE
llm_functions-0.1.21.dist-info/METADATA
llm_functions-0.1.21.dist-info/WHEEL
llm_functions-0.1.21.dist-info/RECORD
